r3d2/__init__.py
r3d2/eos_defns.py
r3d2/riemann_problem.py
r3d2/state.py
r3d2/utils.py
r3d2/wave.py
r3d2-1.0.dist-info/DESCRIPTION.rst
r3d2-1.0.dist-info/METADATA
r3d2-1.0.dist-info/RECORD
r3d2-1.0.dist-info/WHEEL
r3d2-1.0.dist-info/metadata.json
r3d2-1.0.dist-info/top_level.txt
