Metadata-Version: 2.0
Name: r3d2
Version: 1.0
Summary: Relativistic Reactive Riemann problem solver for Deflagrations and Detonations
Home-page: https://github.com/harpolea/r3d2
Author: Alice Harpole, Ian Hawke
Author-email: A.Harpole@soton.ac.uk, I.Hawke@soton.ac.uk
License: MIT
Keywords: relativity riemann solver
Platform: UNKNOWN
Classifier: Development Status :: 4 - Beta
Classifier: Intended Audience :: Science/Research
Classifier: License :: OSI Approved :: MIT License
Classifier: Programming Language :: Python
Classifier: Topic :: Scientific/Engineering :: Physics
Requires-Dist: matplotlib
Requires-Dist: numpy
Requires-Dist: scipy
